zyx_tools/FileTool.py
zyx_tools/OtherTool.py
zyx_tools/SvnTool.py
zyx_tools/__init__.py
zyx_tools/logprint.py
zyx_tools/version.py
zyx_tools-0.0.20.dist-info/LICENSE
zyx_tools-0.0.20.dist-info/METADATA
zyx_tools-0.0.20.dist-info/WHEEL
zyx_tools-0.0.20.dist-info/top_level.txt
zyx_tools-0.0.20.dist-info/RECORD
